{
    "jobId":"{id}",
    "timestamp":"{timeStamp}",
    "pipeline":"indexedPipeline",
    "data":
    [
        {
            "nodeName":"evaladd",
            "batchIndex":2,
            "algorithmName":"eval-alg",
            "result":27
        },
        {
            "nodeName":"evaladd",
            "batchIndex":4,
            "algorithmName":"eval-alg",
            "result":-3
        },
        {
            "nodeName":"evaladd",
            "batchIndex":1,
            "algorithmName":"eval-alg",
            "result":7
        },
        {
            "nodeName":"evaladd",
            "batchIndex":3,
            "algorithmName":"eval-alg",
            "result":55
        }
    ],
    "status":"completed",
    "timeTook":"{timeTook}",
    "storageModule":"@hkube/s3-adapter"
}